bookkeeper/__init__.py
bookkeeper/defparser.py
bookkeeper/ledger.py
bookkeeper/main.py
bookkeeper/txparser.py
pybookkeeper-0.11.0.dist-info/METADATA
pybookkeeper-0.11.0.dist-info/WHEEL
pybookkeeper-0.11.0.dist-info/entry_points.txt
pybookkeeper-0.11.0.dist-info/top_level.txt
pybookkeeper-0.11.0.dist-info/RECORD
