Metadata-Version: 2.4
Name: pybookkeeper
Version: 0.11.0
Summary: Utility for small-scale Finnish double-ledger bookkeeping
Author-email: "Sami J. Lehtinen" <sjl+bookkeeper@iki.fi>
Project-URL: repository, https://github.com/sjlehtin/bookkeeper.git
Classifier: Programming Language :: Python :: 3
Classifier: Operating System :: OS Independent
Requires-Python: >=3.10
Requires-Dist: click
Requires-Dist: lark-parser
Provides-Extra: dev
Requires-Dist: pytest; extra == "dev"
Requires-Dist: tox; extra == "dev"
Requires-Dist: build; extra == "dev"
Requires-Dist: tox-uv; extra == "dev"
